Workbook

Sheet PL
B1: PACKING LIST
B2: SELLER
B3: U.S.K. TEKSTIL SANAYI VE TICARET LIMITED SIRKETI | G3: DATE | H3: 46094
B4: DEMIRTAS DUMLUPINAR OSB, MUSTAFA KARAER CD.,
B5: NO.49/, OSMANGAZI, 16110, BURSA, TURKIYE | G5: INVOICE NO | H5: USI2026000000006
B6: VAT. 8830038249 ERTUGRULGAZI / TRD.REG.NO. 40640
B7: PHONE. +90 224 2612100 / E-MAIL. sales@usktekstil.com.tr
B8: BUYER | F8: DELIVERY ADRESS / CONSIGNE
B9: G.K FASHION LTD. | F9: NEW GK FASHION SARL.
B10: 434 THURMASTONE BOULEVARD, | F10: LOT 258, ZONE INDUSTTRIELLE DE GZENAYA,
B11: LECEISTER LE4 9LE, UNITED KINGDOM | F11: 90000, TANGIER, MOROCCO
B12: VAT NO. 973998537 | F12: CONTACT PERSON. FATHIA QULAD MEHDI
B13: PHONE. +44 079128-72750 E-MAIL. sonu@gkfashionltd.com | F13: PHONE. 0539 40 06 45 / E-MAIL. fatimek1975@gmail.com
B15: ROLL | C15: DESIGN/COLOR/COMPOSITION | D15: ORDER NO | E15: LOT | F15: BAR NO | G15: METERS | H15: NET KG | I15: GROSS KG
B16: 1 | C16: G-2714 / LEIA 1/ DARK BROWN / 95%PES 5%EA / 145CM | D16: PO. 3633 / DOCKER NO. 2192 | E16: 1 | F16: 1580181 | G16: 75.5 | H16: 15.2 | I16: =(H16+0.5) -> 15.7
B17: 2 | C17: G-2714 / LEIA 1/ DARK BROWN / 95%PES 5%EA / 145CM | D17: PO. 3633 / DOCKER NO. 2192 | E17: 1 | F17: 1580182 | G17: 90.96 | H17: 16.1 | I17: =(H17+0.5) -> 16.6
B18: 3 | C18: G-2714 / LEIA 1/ DARK BROWN / 95%PES 5%EA / 145CM | D18: PO. 3633 / DOCKER NO. 2192 | E18: 1 | F18: 1580183 | G18: 80 | H18: 14.2 | I18: =(H18+0.5) -> 14.7
B19: 4 | C19: G-2714 / LEIA 1/ DARK BROWN / 95%PES 5%EA / 145CM | D19: PO. 3633 / DOCKER NO. 2192 | E19: 1 | F19: 1580190 | G19: 82.85 | H19: 14.85 | I19: =(H19+0.5) -> 15.35
B20: 5 | C20: G-2714 / LEIA 1/ DARK BROWN / 95%PES 5%EA / 145CM | D20: PO. 3633 / DOCKER NO. 2192 | E20: 1 | F20: 1580198 | G20: 82.42 | H20: 15.05 | I20: =(H20+0.5) -> 15.55
B21: 6 | C21: G-2714 / LEIA 1/ DARK BROWN / 95%PES 5%EA / 145CM | D21: PO. 3633 / DOCKER NO. 2192 | E21: 1 | F21: 1580201 | G21: 117.5 | H21: 18.95 | I21: =(H21+0.5) -> 19.45
B22: 7 | C22: G-2714 / LEIA 1/ DARK BROWN / 95%PES 5%EA / 145CM | D22: PO. 3633 / DOCKER NO. 2192 | E22: 1 | F22: 1580204 | G22: 77 | H22: 13.8 | I22: =(H22+0.5) -> 14.3
B23: 8 | C23: G-2714 / LEIA 1/ DARK BROWN / 95%PES 5%EA / 145CM | D23: PO. 3633 / DOCKER NO. 2192 | E23: 1 | F23: 1580205 | G23: 94.79 | H23: 15.9 | I23: =(H23+0.5) -> 16.4
B24: 9 | C24: G-2714 / LEIA 1/ DARK BROWN / 95%PES 5%EA / 145CM | D24: PO. 3633 / DOCKER NO. 2192 | E24: 1 | F24: 1580207 | G24: 47.53 | H24: 8.8 | I24: =(H24+0.5) -> 9.3
B25: 10 | C25: G-2714 / LEIA 1/ DARK BROWN / 95%PES 5%EA / 145CM | D25: PO. 3633 / DOCKER NO. 2192 | E25: 1 | F25: 1580278 | G25: 40 | H25: 8 | I25: =(H25+0.5) -> 8.5
G26: =SUM(G16:G25) -> 788.55 | H26: =SUM(H16:H25) -> 140.85 | I26: =SUM(I16:I25) -> 145.85
B28: THE GOODS ARE OF TURKISH ORIGIN | G28: TOTAL METERS | I28: =G26 -> 788.55
G29: TOTAL NET KG | I29: =H26 -> 140.85
G30: TOTAL GROSS KG | I30: =I26 -> 145.85
G31: TOTAL ROLLS | I31: 10

Sheet CI
B2: SELLER TITLE: | F2: COMMERCIAL INVOICE
B3: USK TEKSTIL SANAYI VE TICARET LIMITED SIRKETI
B4: DEMİRTAŞ DUMLUPINAR OSB., MUSTAFA KARAER CD.,
B5: NO.49/2, OSMANGAZİ, 16110, BURSA
B6: TURKIYE | D6: TRD.REG.NO. 40640
B7: VAT. 883 003 8249 ERTUGRULGAZI | L7: INVOICE NO
B8: PHONE. +90 224 2612100 | L8: USI2026000000006
B9: CUSTOMER TITLE : | F9: DELIVERY TITLE & ADDRESS:
B10: GK FASHION LTD. | F10: NEW GK FASHION SARL. | L10: INVOICE DATE
B11: 434-438 THURMASTONE BOULEVARD, | F11: LOT 258, ZONE INDUSTTRIELLE DE GZENAYA | L11: 46094
B12: LECEISTER LE4 9LE, | F12: 90000 TANGIER
B13: UNITED KINGDOM | F13: MOROCCO | L13: CUSTOMER PO NO
B14: VAT NO. 973998537 | F14: CONTACT PERSON. FATHIA QULAD MEHDI | L14: 3633 - DOCKER NO. N2192
B15: PHN. +44 079128-72750 E-ML. sonu@gkfashionltd.com | F15: PHN. 0539 40 06 45 / E-ML. fatimek1975@gmail.com
B17: TYPE OF GOODS | C17: ARTICLE NAME | E17: ARTICLE CODE | F17: COLOR CODE | G17: ARTICLE COMPOSITION | I17: PRICE | J17: USD | K17: QUANTITY | M17: MTR | N17: TOTAL AMOUNT
B19: WOVEN FABRIC 145CM / 120GRM | C19: LEIA 1 | E19: G-2714 | F19: DARK BROWN | G19: 95%PES 5%EA | I19: 2.35 | J19: =$J$17 -> USD | K19: 788.55 | M19: =$M$17 -> MTR | N19: =K19*I19 -> 1853.0925 | O19: =$J$17 -> USD
J20: =$J$17 -> USD | M20: =$M$17 -> MTR | N20: =K20*I20 -> 0 | O20: =$J$17 -> USD
B21: ALL GOODS MADE IN TURKEY, OUR TEXTILES ARE AZO FREE. | G21: GRAND TOTALS | K21: =SUM(K19:K20) -> 788.55 | M21: =$M$17 -> MTR | N21: =SUM(N19:N20) -> 1853.0925 | O21: =$J$17 -> USD
B22: AMOUNT IN WORDS | C22: ONE THOUSAND, EIGHT HUNDREDS,FIFTYTHREE US DOLARS AND NINE CENTS
B24: PAYMENT TERMS: | D24: 90 DAYS NET | I24: BANK NAME: | L24: =VLOOKUP(J17, Data!A:G, 2, 0) -> T. GARANTI BANKASI A.S.
B25: DELIVERY TERMS: | D25: DAP TANGIER, MOROCCO | I25: BRANCH NAME & NO: | L25: =VLOOKUP(J17, Data!A:G, 3, 0) -> BURSA TICARI BRANCH - 1667
B26: TRANSPORTER: | D26: DACHSER LOGISTIC | I26: ACCOUNT NO: | L26: =VLOOKUP(J17, Data!A:G, 5, 0) -> 9001820 | O26: =VLOOKUP(J17, Data!A:G, 6, 0) -> USD
B27: TOTAL GROSS KG: | D27: 145.85 | E27: NUMBER OF ROLLS: | G27: 10 | I27: SWIFT CODE : | L27: =VLOOKUP(J17, Data!A:G, 4, 0) -> TGBATRISXXX
B28: TOTAL NET KG: | D28: 140.85 | E28: NUMBER OF SACKS: | I28: IBAN NO: | L28: =VLOOKUP(J17, Data!A:G, 7, 0) -> TR39 0006 2001 6670 0009 0018 20
I29: THE GOODS ARE OF TURKISH ORIGIN
B31: AUTHORIZED SIGNATURE & STAMP | F31: The exporter of the products covered by this document declares that, except where
F32: otherwise clearly indicated, these products are of Turkish preferential origin.

Sheet KT
B1: KONSIMENTO TALIMATNAMESI
B2: SELLER
B3: U.S.K. TEKSTIL SANAYI VE TICARET LIMITED SIRKETI | G3: DATE | H3: 46094
B4: DEMIRTAS DUMLUPINAR OSB, MUSTAFA KARAER CD.,
B5: NO.49/, OSMANGAZI, 16110, BURSA, TURKIYE | G5: INVOICE NO | H5: USI2026000000006
B6: VAT. 8830038249 ERTUGRULGAZI / TRD.REG.NO. 40640
B7: PHONE. +90 224 2612100 / E-MAIL. sales@usktekstil.com.tr
B8: BUYER | F8: DELIVERY ADRESS / CONSIGNE
B9: G.K FASHION LTD. | F9: NEW GK FASHION SARL.
B10: 434 THURMASTONE BOULEVARD, | F10: LOT 258, ZONE INDUSTTRIELLE DE GZENAYA,
B11: LECEISTER LE4 9LE, UNITED KINGDOM | F11: 90000, TANGIER, MOROCCO
B12: VAT NO. 973998537 | F12: CONTACT PERSON. FATHIA QULAD MEHDI
B13: PHONE. +44 079128-72750 E-MAIL. sonu@gkfashionltd.com | F13: PHONE. 0539 40 06 45 / E-MAIL. fatimek1975@gmail.com
B14: TRANSPORTER COMPANY | F14: CUSTOM AGENCY
B15: DACHSER TURKEY LOJISTIK HIZMETLERI A.S. | F15: HGL GUMRUK MUSAVIRLIGI LOJ. VE DIS TICARET A.S.
B16: MASLAK MH, BUYUKSERE CD., NO.255, NUROL PLAZA, | F16: BEYLIKDUZU MERMERCILER OSB MH., 7. CD., NO.4, K.2
B17: K14, SARIYER, 34485, ISTANBUL, TURKIYE | F17: BEYLIKDUZU, 34524, ISTANBUL, TURKIYE
B18: alper.gundogdu@dachser.com / M. +90 549 6630551 | F18: PHONE. +90 212 8757700 - 304
B19: ozlem.ozdemir@dachser.com / M. +90 530 9157648 | F19: ergun.kavdir@hgl.com.tr
B20: yasemin.dagdelen@dachser.com / M. +90 549 6630553
B22: TYPES OF GOODS | D22: WOWEN FABRIC 95%PES 5% ELASTAN
B23: GTYPE NO | D23: 5407.61.90.90.19 | G23: GOODS SPC. | H23: 145CM WIDTH / 120GR2M
B24: PAYMENT TERMS | D24: 90 DAYS NET | G24: DUE DATE | H24: 46184
B25: DELIVERY TERMS | D25: DAP TANGIER, MOROCCO
B26: TOTAL QUANTITY | D26: 788.55 | E26: MTS
B27: TOTAL AMAOUNT OF INVOICE | D27: 1853.09 | E27: USD
B28: TOTAL GROSS KG | D28: 145.85 | E28: KG | G28: N.OF ROLLS | H28: 10
B29: TOTAL NET KG | D29: 140.85 | E29: KG | G29: N. OF SACKS | H29: -
B30: MANUFACTURER COMPANY | D30: U.S.K. TEKSTIL SANAYI VE TICARET LIMITED SIRKETI
B32: DOCUMENTS NEEDS | D32: EUR 1
B33: NOTES | D33: IN ALL DOCUMENTS, GOODS NAME AND SPECSIFICATIONS WILL BE SAME
B35: THE GOODS ARE OF TURKISH ORIGIN
B36: URUNLER TURKIYE MENSEILIDIR

Sheet Data
A3: CURRENCY | B3: BANK NAME: | C3: BRANCH NAME & NO: | D3: SWIFT CODE: | E3: ACCOUNT NO: | F3: NAME | G3: IBAN NO:
A4: USD | B4: T. GARANTI BANKASI A.S. | C4: BURSA TICARI BRANCH - 1667 | D4: TGBATRISXXX | E4: 9001820 | F4: USD | G4: TR39 0006 2001 6670 0009 0018 20
A5: EUR | B5: T. GARANTI BANKASI A.S. | C5: BURSA TICARI BRANCH - 1667 | D5: TGBATRISXXX | E5: 9094319 | F5: EURO | G5: TR25 0006 2001 6670 0009 0943 19
A6: GBP | B6: T.C. ZIRAAT BANKASI | C6: MERINOS BRANCH - 2062 | D6: TCZBTR2A | E6: 60610959-5051 | F6: GBP | G6: TR68 0001 0020 6260 6109 5950 51
A7: TL | B7: T. GARANTI BANKASI A.S. | C7: BURSA TICARI BRANCH - 1667 | D7: TGBATRISXXX | E7: 6298283 | F7: TRY | G7: TR31 0006 2001 6670 0006 2982 83
A8: $ | B8: NA | C8: NA | D8: NA | E8: NA | F8: US ($) | G8: NA
A9: € | B9: NA | C9: NA | D9: NA | E9: NA | F9: EU (€) | G9: NA

Sheet CI (2)
B2: SELLER TITLE: | F2: COMMERCIAL INVOICE
B3: USK TEKSTIL SANAYI VE TICARET LIMITED SIRKETI
B4: DEMİRTAŞ DUMLUPINAR OSB., MUSTAFA KARAER CD.,
B5: NO.49/2, OSMANGAZİ, 16110, BURSA
B6: TURKIYE | D6: TRD.REG.NO. 40640
B7: VAT. 883 003 8249 ERTUGRULGAZI | L7: INVOICE NO
B8: PHONE. +90 224 2612100 | L8: USI2026000000006
B9: CUSTOMER TITLE : | F9: DELIVERY TITLE & ADDRESS:
B10: GK FASHION LTD. | F10: NEW GK FASHION SARL. | L10: INVOICE DATE
B11: 434-438 THURMASTONE BOULEVARD, | F11: LOT 258, ZONE INDUSTTRIELLE DE GZENAYA | L11: 46094
B12: LECEISTER LE4 9LE, | F12: 90000 TANGIER
B13: UNITED KINGDOM | F13: MOROCCO | L13: CUSTOMER PO NO
B14: VAT NO. 973998537 | F14: CONTACT PERSON. FATHIA QULAD MEHDI | L14: 3633 - DOCKER NO. N2192
B15: PHN. +44 079128-72750 E-ML. sonu@gkfashionltd.com | F15: PHN. 0539 40 06 45 / E-ML. fatimek1975@gmail.com
B17: TYPE OF GOODS | C17: ARTICLE NAME | E17: ARTICLE CODE | F17: COLOR CODE | G17: ARTICLE COMPOSITION | I17: PRICE | J17: USD | K17: QUANTITY | M17: MTR | N17: TOTAL AMOUNT
B19: WOVEN FABRIC 145CM / 120GRM | C19: LEIA 1 | E19: G-2714 | F19: DARK BROWN | G19: 95%PES 5%EA | I19: 2.35 | J19: =$J$17 -> USD | K19: 788.55 | M19: =$M$17 -> MTR | N19: =K19*I19 -> 1853.0925 | O19: =$J$17 -> USD
J20: =$J$17 -> USD | M20: =$M$17 -> MTR | N20: =K20*I20 -> 0 | O20: =$J$17 -> USD
B21: ALL GOODS MADE IN TURKEY, OUR TEXTILES ARE AZO FREE. | G21: GRAND TOTALS | K21: =SUM(K19:K20) -> 788.55 | M21: =$M$17 -> MTR | N21: =SUM(N19:N20) -> 1853.0925 | O21: =$J$17 -> USD
B22: AMOUNT IN WORDS | C22: ONE THOUSAND, EIGHT HUNDREDS,FIFTYTHREE US DOLARS AND NINE CENTS
B24: PAYMENT TERMS: | D24: 90 DAYS NET | I24: BANK NAME: | L24: =VLOOKUP(J17, Data!A:G, 2, 0) -> T. GARANTI BANKASI A.S.
B25: DELIVERY TERMS: | D25: DAP TANGIER, MOROCCO | I25: BRANCH NAME & NO: | L25: =VLOOKUP(J17, Data!A:G, 3, 0) -> BURSA TICARI BRANCH - 1667
B26: TRANSPORTER: | D26: DACHSER LOGISTIC | I26: ACCOUNT NO: | L26: =VLOOKUP(J17, Data!A:G, 5, 0) -> 9001820 | O26: =VLOOKUP(J17, Data!A:G, 6, 0) -> USD
B27: TOTAL GROSS KG: | D27: 145.85 | E27: NUMBER OF ROLLS: | G27: 10 | I27: SWIFT CODE : | L27: =VLOOKUP(J17, Data!A:G, 4, 0) -> TGBATRISXXX
B28: TOTAL NET KG: | D28: 140.85 | E28: NUMBER OF SACKS: | I28: IBAN NO: | L28: =VLOOKUP(J17, Data!A:G, 7, 0) -> TR39 0006 2001 6670 0009 0018 20
I29: THE GOODS ARE OF TURKISH ORIGIN
B31: AUTHORIZED SIGNATURE & STAMP | F31: The exporter of the products covered by this document declares that, except where
F32: otherwise clearly indicated, these products are of Turkish preferential origin.

Sheet LEIA 1
A1: BarNo | B1: EN BOY | C1: ÇAP
A2: 1580181 | B2: 141 | C2: 14.940633
A3: 1580182 | B3: 141 | C3: 18
A4: 1580183 | B4: 141 | C4: 15.831135
A5: 1580190 | B5: 141 | C5: 16.395119
A6: 1580198 | B6: 141 | C6: 16.310026
A7: 1580201 | B7: 141 | C7: 23.251979
A8: 1580204 | B8: 141 | C8: 15.237467
A9: 1580205 | B9: 141 | C9: 18.757916
A10: 1580207 | B10: 141 | C10: 9.4056728
A11: 1580278 | B11: 141 | C11: 9.4056728
A12: 10
